[
  {
    "timestamp": "14-34-45-2354",
    "node": "node3",
    "distance": "111.84",
    "cordinal direction": "North"
  },
  {
    "timestamp": "14-34-45-2479",
    "node": "node1",
    "distance": "84.28",
    "cordinal direction": "West"
  },
  {
    "timestamp": "14-34-45-2489",
    "node": "node4",
    "distance": "102.38",
    "cordinal direction": "North"
  },
  {
    "timestamp": "14-34-45-2489",
    "node": "node2",
    "distance": "95.52",
    "cordinal direction": "East"
  },
  {
    "timestamp": "14-34-47-3215",
    "node": "node3",
    "distance": "92.11",
    "cordinal direction": "North"
  },
  {
    "timestamp": "14-34-47-3215",
    "node": "node1",
    "distance": "104.23",
    "cordinal direction": "West"
  },
  {
    "timestamp": "14-34-47-3215",
    "node": "node4",
    "distance": "104.04",
    "cordinal direction": "West"
  },
  {
    "timestamp": "14-34-47-3215",
    "node": "node2",
    "distance": "92.33",
    "cordinal direction": "South"
  },
  {
    "timestamp": "14-34-48-3229",
    "node": "node3",
    "distance": "72.54",
    "cordinal direction": "North"
  },
  {
    "timestamp": "14-34-48-3229",
    "node": "node1",
    "distance": "124.19",
    "cordinal direction": "West"
  },
  {
    "timestamp": "14-34-48-3229",
    "node": "node4",
    "distance": "109.35",
    "cordinal direction": "West"
  },
  {
    "timestamp": "14-34-48-3229",
    "node": "node2",
    "distance": "93.36",
    "cordinal direction": "South"
  },
  {
    "timestamp": "14-34-49-3206",
    "node": "node3",
    "distance": "52.65",
    "cordinal direction": "North"
  },
  {
    "timestamp": "14-34-49-3206",
    "node": "node1",
    "distance": "144.12",
    "cordinal direction": "West"
  },
  {
    "timestamp": "14-34-49-3206",
    "node": "node4",
    "distance": "115.23",
    "cordinal direction": "West"
  },
  {
    "timestamp": "14-34-49-3206",
    "node": "node2",
    "distance": "101.12",
    "cordinal direction": "South"
  },
  {
    "timestamp": "14-34-50-3211",
    "node": "node3",
    "distance": "32.88",
    "cordinal direction": "North"
  },
  {
    "timestamp": "14-34-50-3211",
    "node": "node1",
    "distance": "164.07",
    "cordinal direction": "West"
  },
  {
    "timestamp": "14-34-50-3211",
    "node": "node4",
    "distance": "124.07",
    "cordinal direction": "West"
  },
  {
    "timestamp": "14-34-50-3211",
    "node": "node2",
    "distance": "111.92",
    "cordinal direction": "South"
  },
  {
    "timestamp": "14-34-51-3244",
    "node": "node3",
    "distance": "34.05",
    "cordinal direction": "North"
  },
  {
    "timestamp": "14-34-51-3244",
    "node": "node1",
    "distance": "174.53",
    "cordinal direction": "West"
  },
  {
    "timestamp": "14-34-51-3244",
    "node": "node4",
    "distance": "143.99",
    "cordinal direction": "West"
  },
  {
    "timestamp": "14-34-51-3244",
    "node": "node2",
    "distance": "103.96",
    "cordinal direction": "South"
  },
  {
    "timestamp": "14-34-52-3223",
    "node": "node3",
    "distance": "44.92",
    "cordinal direction": "North"
  },
  {
    "timestamp": "14-34-52-3223",
    "node": "node1",
    "distance": "186.55",
    "cordinal direction": "West"
  },
  {
    "timestamp": "14-34-52-3223",
    "node": "node4",
    "distance": "163.92",
    "cordinal direction": "West"
  },
  {
    "timestamp": "14-34-52-3223",
    "node": "node2",
    "distance": "99.41",
    "cordinal direction": "South"
  },
  {
    "timestamp": "14-34-53-3373",
    "node": "node3",
    "distance": "39.72",
    "cordinal direction": "North"
  },
  {
    "timestamp": "14-34-53-3373",
    "node": "node1",
    "distance": "170.32",
    "cordinal direction": "West"
  },
  {
    "timestamp": "14-34-53-3373",
    "node": "node4",
    "distance": "144.44",
    "cordinal direction": "West"
  },
  {
    "timestamp": "14-34-53-3373",
    "node": "node2",
    "distance": "98.28",
    "cordinal direction": "South"
  },
  {
    "timestamp": "14-34-54-3211",
    "node": "node3",
    "distance": "43.81",
    "cordinal direction": "North"
  },
  {
    "timestamp": "14-34-54-3211",
    "node": "node1",
    "distance": "154.98",
    "cordinal direction": "West"
  },
  {
    "timestamp": "14-34-54-3211",
    "node": "node4",
    "distance": "125.13",
    "cordinal direction": "West"
  },
  {
    "timestamp": "14-34-54-3211",
    "node": "node2",
    "distance": "101.13",
    "cordinal direction": "South"
  },
  {
    "timestamp": "14-34-55-3258",
    "node": "node3",
    "distance": "41.67",
    "cordinal direction": "East"
  },
  {
    "timestamp": "14-34-55-3258",
    "node": "node1",
    "distance": "154.89",
    "cordinal direction": "South"
  },
  {
    "timestamp": "14-34-55-3258",
    "node": "node4",
    "distance": "107.82",
    "cordinal direction": "West"
  },
  {
    "timestamp": "14-34-55-3258",
    "node": "node2",
    "distance": "118.51",
    "cordinal direction": "South"
  },
  {
    "timestamp": "14-34-56-3217",
    "node": "node3",
    "distance": "48.33",
    "cordinal direction": "East"
  },
  {
    "timestamp": "14-34-56-3217",
    "node": "node1",
    "distance": "157.35",
    "cordinal direction": "South"
  },
  {
    "timestamp": "14-34-56-3217",
    "node": "node4",
    "distance": "91.60",
    "cordinal direction": "West"
  },
  {
    "timestamp": "14-34-56-3217",
    "node": "node2",
    "distance": "136.60",
    "cordinal direction": "South"
  },
  {
    "timestamp": "14-34-57-3225",
    "node": "node3",
    "distance": "67.46",
    "cordinal direction": "East"
  },
  {
    "timestamp": "14-34-57-3225",
    "node": "node1",
    "distance": "138.93",
    "cordinal direction": "South"
  },
  {
    "timestamp": "14-34-57-3225",
    "node": "node4",
    "distance": "77.32",
    "cordinal direction": "West"
  },
  {
    "timestamp": "14-34-57-3225",
    "node": "node2",
    "distance": "133.66",
    "cordinal direction": "South"
  },
  {
    "timestamp": "14-34-58-3239",
    "node": "node3",
    "distance": "86.97",
    "cordinal direction": "East"
  },
  {
    "timestamp": "14-34-58-3239",
    "node": "node1",
    "distance": "121.00",
    "cordinal direction": "South"
  },
  {
    "timestamp": "14-34-58-3239",
    "node": "node4",
    "distance": "66.03",
    "cordinal direction": "West"
  },
  {
    "timestamp": "14-34-58-3239",
    "node": "node2",
    "distance": "133.65",
    "cordinal direction": "South"
  },
  {
    "timestamp": "14-34-59-3230",
    "node": "node3",
    "distance": "67.73",
    "cordinal direction": "East"
  },
  {
    "timestamp": "14-34-59-3230",
    "node": "node1",
    "distance": "139.32",
    "cordinal direction": "South"
  },
  {
    "timestamp": "14-34-59-3230",
    "node": "node4",
    "distance": "76.55",
    "cordinal direction": "West"
  },
  {
    "timestamp": "14-34-59-3230",
    "node": "node2",
    "distance": "134.64",
    "cordinal direction": "South"
  },
  {
    "timestamp": "14-35-00-3227",
    "node": "node3",
    "distance": "49.08",
    "cordinal direction": "East"
  },
  {
    "timestamp": "14-35-00-3227",
    "node": "node1",
    "distance": "158.04",
    "cordinal direction": "South"
  },
  {
    "timestamp": "14-35-00-3227",
    "node": "node4",
    "distance": "90.31",
    "cordinal direction": "West"
  },
  {
    "timestamp": "14-35-00-3227",
    "node": "node2",
    "distance": "138.51",
    "cordinal direction": "South"
  },
  {
    "timestamp": "14-35-01-3240",
    "node": "node3",
    "distance": "41.67",
    "cordinal direction": "East"
  },
  {
    "timestamp": "14-35-01-3240",
    "node": "node1",
    "distance": "155.31",
    "cordinal direction": "South"
  },
  {
    "timestamp": "14-35-01-3240",
    "node": "node4",
    "distance": "106.34",
    "cordinal direction": "West"
  },
  {
    "timestamp": "14-35-01-3240",
    "node": "node2",
    "distance": "120.37",
    "cordinal direction": "South"
  },
  {
    "timestamp": "14-35-02-3218",
    "node": "node3",
    "distance": "42.97",
    "cordinal direction": "North"
  },
  {
    "timestamp": "14-35-02-3218",
    "node": "node1",
    "distance": "155.12",
    "cordinal direction": "West"
  },
  {
    "timestamp": "14-35-02-3218",
    "node": "node4",
    "distance": "123.52",
    "cordinal direction": "West"
  },
  {
    "timestamp": "14-35-02-3218",
    "node": "node2",
    "distance": "102.92",
    "cordinal direction": "South"
  },
  {
    "timestamp": "14-35-03-3222",
    "node": "node3",
    "distance": "38.29",
    "cordinal direction": "East"
  },
  {
    "timestamp": "14-35-03-3222",
    "node": "node1",
    "distance": "158.66",
    "cordinal direction": "South"
  },
  {
    "timestamp": "14-35-03-3222",
    "node": "node4",
    "distance": "108.47",
    "cordinal direction": "West"
  },
  {
    "timestamp": "14-35-03-3222",
    "node": "node2",
    "distance": "121.68",
    "cordinal direction": "South"
  },
  {
    "timestamp": "14-35-04-3224",
    "node": "node3",
    "distance": "43.20",
    "cordinal direction": "East"
  },
  {
    "timestamp": "14-35-04-3224",
    "node": "node1",
    "distance": "164.57",
    "cordinal direction": "South"
  },
  {
    "timestamp": "14-35-04-3224",
    "node": "node4",
    "distance": "95.24",
    "cordinal direction": "West"
  },
  {
    "timestamp": "14-35-04-3224",
    "node": "node2",
    "distance": "140.79",
    "cordinal direction": "South"
  },
  {
    "timestamp": "14-35-05-3220",
    "node": "node3",
    "distance": "41.90",
    "cordinal direction": "East"
  },
  {
    "timestamp": "14-35-05-3220",
    "node": "node1",
    "distance": "182.84",
    "cordinal direction": "South"
  },
  {
    "timestamp": "14-35-05-3220",
    "node": "node4",
    "distance": "99.68",
    "cordinal direction": "West"
  },
  {
    "timestamp": "14-35-05-3220",
    "node": "node2",
    "distance": "158.69",
    "cordinal direction": "South"
  }
]