[
  {
    "timestamp": "14-56-14-8768",
    "node": "node3",
    "distance": "111.84",
    "cordinal direction": "North"
  },
  {
    "timestamp": "14-56-14-8918",
    "node": "node1",
    "distance": "84.28",
    "cordinal direction": "West"
  },
  {
    "timestamp": "14-56-14-8918",
    "node": "node4",
    "distance": "102.38",
    "cordinal direction": "North"
  },
  {
    "timestamp": "14-56-14-8928",
    "node": "node2",
    "distance": "95.52",
    "cordinal direction": "East"
  },
  {
    "timestamp": "14-56-17-0656",
    "node": "node3",
    "distance": "94.04",
    "cordinal direction": "North"
  },
  {
    "timestamp": "14-56-17-0656",
    "node": "node1",
    "distance": "103.23",
    "cordinal direction": "West"
  },
  {
    "timestamp": "14-56-17-0656",
    "node": "node4",
    "distance": "109.36",
    "cordinal direction": "West"
  },
  {
    "timestamp": "14-56-17-0656",
    "node": "node2",
    "distance": "86.85",
    "cordinal direction": "South"
  },
  {
    "timestamp": "14-56-18-0713",
    "node": "node3",
    "distance": "77.32",
    "cordinal direction": "North"
  },
  {
    "timestamp": "14-56-18-0713",
    "node": "node1",
    "distance": "122.52",
    "cordinal direction": "West"
  },
  {
    "timestamp": "14-56-18-0713",
    "node": "node4",
    "distance": "119.30",
    "cordinal direction": "West"
  },
  {
    "timestamp": "14-56-18-0713",
    "node": "node2",
    "distance": "82.17",
    "cordinal direction": "South"
  },
  {
    "timestamp": "14-56-19-0663",
    "node": "node3",
    "distance": "67.72",
    "cordinal direction": "North"
  },
  {
    "timestamp": "14-56-19-0663",
    "node": "node1",
    "distance": "139.92",
    "cordinal direction": "West"
  },
  {
    "timestamp": "14-56-19-0663",
    "node": "node4",
    "distance": "135.54",
    "cordinal direction": "West"
  },
  {
    "timestamp": "14-56-19-0663",
    "node": "node2",
    "distance": "76.06",
    "cordinal direction": "South"
  },
  {
    "timestamp": "14-56-20-0696",
    "node": "node3",
    "distance": "63.12",
    "cordinal direction": "North"
  },
  {
    "timestamp": "14-56-20-0696",
    "node": "node1",
    "distance": "157.94",
    "cordinal direction": "West"
  },
  {
    "timestamp": "14-56-20-0696",
    "node": "node4",
    "distance": "152.68",
    "cordinal direction": "West"
  },
  {
    "timestamp": "14-56-20-0696",
    "node": "node2",
    "distance": "74.88",
    "cordinal direction": "South"
  },
  {
    "timestamp": "14-56-21-0677",
    "node": "node3",
    "distance": "52.23",
    "cordinal direction": "North"
  },
  {
    "timestamp": "14-56-21-0677",
    "node": "node1",
    "distance": "152.15",
    "cordinal direction": "West"
  },
  {
    "timestamp": "14-56-21-0677",
    "node": "node4",
    "distance": "133.62",
    "cordinal direction": "West"
  },
  {
    "timestamp": "14-56-21-0677",
    "node": "node2",
    "distance": "89.36",
    "cordinal direction": "South"
  },
  {
    "timestamp": "14-56-22-0649",
    "node": "node3",
    "distance": "47.54",
    "cordinal direction": "North"
  },
  {
    "timestamp": "14-56-22-0649",
    "node": "node1",
    "distance": "148.81",
    "cordinal direction": "West"
  },
  {
    "timestamp": "14-56-22-0649",
    "node": "node4",
    "distance": "114.88",
    "cordinal direction": "West"
  },
  {
    "timestamp": "14-56-22-0649",
    "node": "node2",
    "distance": "105.64",
    "cordinal direction": "South"
  },
  {
    "timestamp": "14-56-23-0657",
    "node": "node3",
    "distance": "31.60",
    "cordinal direction": "East"
  },
  {
    "timestamp": "14-56-23-0657",
    "node": "node1",
    "distance": "165.15",
    "cordinal direction": "South"
  },
  {
    "timestamp": "14-56-23-0657",
    "node": "node4",
    "distance": "113.31",
    "cordinal direction": "West"
  },
  {
    "timestamp": "14-56-23-0657",
    "node": "node2",
    "distance": "123.91",
    "cordinal direction": "South"
  },
  {
    "timestamp": "14-56-24-0661",
    "node": "node3",
    "distance": "22.86",
    "cordinal direction": "East"
  },
  {
    "timestamp": "14-56-24-0661",
    "node": "node1",
    "distance": "182.21",
    "cordinal direction": "South"
  },
  {
    "timestamp": "14-56-24-0661",
    "node": "node4",
    "distance": "115.21",
    "cordinal direction": "West"
  },
  {
    "timestamp": "14-56-24-0661",
    "node": "node2",
    "distance": "142.63",
    "cordinal direction": "South"
  },
  {
    "timestamp": "14-56-25-0696",
    "node": "node3",
    "distance": "32.99",
    "cordinal direction": "East"
  },
  {
    "timestamp": "14-56-25-0696",
    "node": "node1",
    "distance": "196.47",
    "cordinal direction": "South"
  },
  {
    "timestamp": "14-56-25-0696",
    "node": "node4",
    "distance": "114.67",
    "cordinal direction": "West"
  },
  {
    "timestamp": "14-56-25-0696",
    "node": "node2",
    "distance": "162.62",
    "cordinal direction": "South"
  },
  {
    "timestamp": "14-56-26-0669",
    "node": "node3",
    "distance": "49.42",
    "cordinal direction": "South"
  },
  {
    "timestamp": "14-56-26-0679",
    "node": "node1",
    "distance": "211.66",
    "cordinal direction": "South"
  },
  {
    "timestamp": "14-56-26-0679",
    "node": "node4",
    "distance": "117.55",
    "cordinal direction": "West"
  },
  {
    "timestamp": "14-56-26-0679",
    "node": "node2",
    "distance": "182.61",
    "cordinal direction": "South"
  },
  {
    "timestamp": "14-56-27-0686",
    "node": "node3",
    "distance": "44.85",
    "cordinal direction": "South"
  },
  {
    "timestamp": "14-56-27-0686",
    "node": "node1",
    "distance": "225.50",
    "cordinal direction": "South"
  },
  {
    "timestamp": "14-56-27-0686",
    "node": "node4",
    "distance": "137.29",
    "cordinal direction": "West"
  },
  {
    "timestamp": "14-56-27-0686",
    "node": "node2",
    "distance": "184.15",
    "cordinal direction": "South"
  },
  {
    "timestamp": "14-56-28-0667",
    "node": "node3",
    "distance": "48.63",
    "cordinal direction": "South"
  },
  {
    "timestamp": "14-56-28-0667",
    "node": "node1",
    "distance": "240.20",
    "cordinal direction": "South"
  },
  {
    "timestamp": "14-56-28-0667",
    "node": "node4",
    "distance": "157.09",
    "cordinal direction": "West"
  },
  {
    "timestamp": "14-56-28-0667",
    "node": "node2",
    "distance": "187.81",
    "cordinal direction": "South"
  },
  {
    "timestamp": "14-56-29-0649",
    "node": "node3",
    "distance": "62.65",
    "cordinal direction": "South"
  },
  {
    "timestamp": "14-56-29-0659",
    "node": "node1",
    "distance": "244.58",
    "cordinal direction": "South"
  },
  {
    "timestamp": "14-56-29-0659",
    "node": "node4",
    "distance": "150.34",
    "cordinal direction": "West"
  },
  {
    "timestamp": "14-56-29-0659",
    "node": "node2",
    "distance": "202.62",
    "cordinal direction": "South"
  },
  {
    "timestamp": "14-56-30-0689",
    "node": "node3",
    "distance": "79.25",
    "cordinal direction": "South"
  },
  {
    "timestamp": "14-56-30-0689",
    "node": "node1",
    "distance": "250.48",
    "cordinal direction": "South"
  },
  {
    "timestamp": "14-56-30-0689",
    "node": "node4",
    "distance": "146.02",
    "cordinal direction": "West"
  },
  {
    "timestamp": "14-56-30-0689",
    "node": "node2",
    "distance": "218.25",
    "cordinal direction": "South"
  },
  {
    "timestamp": "14-56-31-0662",
    "node": "node3",
    "distance": "98.35",
    "cordinal direction": "South"
  },
  {
    "timestamp": "14-56-31-0662",
    "node": "node1",
    "distance": "269.17",
    "cordinal direction": "South"
  },
  {
    "timestamp": "14-56-31-0662",
    "node": "node4",
    "distance": "159.67",
    "cordinal direction": "West"
  },
  {
    "timestamp": "14-56-31-0662",
    "node": "node2",
    "distance": "237.85",
    "cordinal direction": "South"
  },
  {
    "timestamp": "14-56-32-0751",
    "node": "node3",
    "distance": "117.75",
    "cordinal direction": "South"
  },
  {
    "timestamp": "14-56-32-0761",
    "node": "node1",
    "distance": "288.03",
    "cordinal direction": "South"
  },
  {
    "timestamp": "14-56-32-0761",
    "node": "node4",
    "distance": "174.54",
    "cordinal direction": "West"
  },
  {
    "timestamp": "14-56-32-0761",
    "node": "node2",
    "distance": "257.51",
    "cordinal direction": "South"
  },
  {
    "timestamp": "14-56-33-0662",
    "node": "node3",
    "distance": "130.50",
    "cordinal direction": "South"
  },
  {
    "timestamp": "14-56-33-0662",
    "node": "node1",
    "distance": "290.23",
    "cordinal direction": "South"
  },
  {
    "timestamp": "14-56-33-0662",
    "node": "node4",
    "distance": "169.89",
    "cordinal direction": "South"
  },
  {
    "timestamp": "14-56-33-0662",
    "node": "node2",
    "distance": "269.00",
    "cordinal direction": "South"
  },
  {
    "timestamp": "14-56-34-0662",
    "node": "node3",
    "distance": "144.89",
    "cordinal direction": "South"
  },
  {
    "timestamp": "14-56-34-0662",
    "node": "node1",
    "distance": "293.77",
    "cordinal direction": "South"
  },
  {
    "timestamp": "14-56-34-0662",
    "node": "node4",
    "distance": "167.51",
    "cordinal direction": "South"
  },
  {
    "timestamp": "14-56-34-0662",
    "node": "node2",
    "distance": "281.45",
    "cordinal direction": "South"
  },
  {
    "timestamp": "14-56-35-0650",
    "node": "node3",
    "distance": "132.98",
    "cordinal direction": "South"
  },
  {
    "timestamp": "14-56-35-0650",
    "node": "node1",
    "distance": "293.37",
    "cordinal direction": "South"
  },
  {
    "timestamp": "14-56-35-0650",
    "node": "node4",
    "distance": "172.94",
    "cordinal direction": "South"
  },
  {
    "timestamp": "14-56-35-0650",
    "node": "node2",
    "distance": "271.67",
    "cordinal direction": "South"
  }
]