[
  {
    "timestamp": "09-59-57",
    "x": 7.30000019,
    "y": 12.1999998
  },
  {
    "timestamp": "10-00-00",
    "x": 17.7678127,
    "y": -4.84187269
  },
  {
    "timestamp": "10-00-01",
    "x": 28.2356281,
    "y": -21.8837452
  },
  {
    "timestamp": "10-00-02",
    "x": 21.0397739,
    "y": -3.22310448
  },
  {
    "timestamp": "10-00-03",
    "x": 13.8439198,
    "y": 15.4375372
  },
  {
    "timestamp": "10-00-04",
    "x": -1.79377782,
    "y": 2.9690938
  },
  {
    "timestamp": "10-00-05",
    "x": -17.4314709,
    "y": -9.49935818
  },
  {
    "timestamp": "10-00-06",
    "x": -23.6366482,
    "y": 9.51368523
  },
  {
    "timestamp": "10-00-07",
    "x": -29.8418255,
    "y": 28.5267086
  },
  {
    "timestamp": "10-00-08",
    "x": -37.5818443,
    "y": 46.9682922
  },
  {
    "timestamp": "10-00-09",
    "x": -45.3218651,
    "y": 65.4098892
  },
  {
    "timestamp": "10-00-10",
    "x": -58.8985634,
    "y": 50.7240677
  },
  {
    "timestamp": "10-00-11",
    "x": -72.4751434,
    "y": 36.0382462
  },
  {
    "timestamp": "10-00-12",
    "x": -59.4098053,
    "y": 20.8956852
  },
  {
    "timestamp": "10-00-13",
    "x": -46.3444672,
    "y": 5.75314903
  },
  {
    "timestamp": "10-00-14",
    "x": -64.8615875,
    "y": 13.3104935
  },
  {
    "timestamp": "10-00-15",
    "x": -83.378891,
    "y": 20.8678074
  },
  {
    "timestamp": "10-00-16",
    "x": -67.2488251,
    "y": 9.04342079
  },
  {
    "timestamp": "10-00-17",
    "x": -51.1186066,
    "y": -2.78094864
  },
  {
    "timestamp": "10-00-18",
    "x": -31.4698639,
    "y": -6.51272011
  }
]